{"2022-11":[{"title":"这里是更新日志","date":"2022-11-13T07:24:00.000Z","link":"/posts/b251992a/"},{"title":"QQ精简嵌入模块版v8.9.15","date":"2022-11-13T07:24:00.000Z","link":"/posts/c0016f87/"},{"title":"我与我的安卓手表","date":"2022-11-13T07:24:00.000Z","link":"/posts/73e14eca/"},{"title":"天空影视全网免费看","date":"2022-11-13T07:24:00.000Z","link":"/posts/5e5bc735/"},{"title":"名著阅读（初中进）","date":"2022-11-13T07:24:00.000Z","link":"/posts/f4938785/"},{"title":"站长的p话","date":"2022-11-13T07:24:00.000Z","link":"/posts/66f05020/"}],"2022-12":[{"title":"分 班","date":"2022-12-15T12:32:21.000Z","link":"/posts/1852b783/"}],"2023-2":[{"title":"TEST","date":"2023-02-06T10:48:37.000Z","link":"/posts/eeea93b8/"}],"2023-8":[{"title":"Hello World","date":"2023-08-16T02:46:06.916Z","link":"/posts/4a17b156/"}]}